{
  "entrypoints": [
    "main"
  ],
  "origins": {
    "2004": [
      532,
      4195,
      2004
    ],
    "2529": [
      532,
      3089,
      6103,
      7654,
      8610,
      2529
    ],
    "4972": [
      4972
    ],
    "7654": [
      532,
      2529,
      3085,
      3089,
      6103,
      7918,
      8610,
      7654
    ],
    "17896441": [
      532,
      7654,
      7918
    ],
    "59362658": [
      2267
    ],
    "main": [
      532,
      1303,
      179
    ],
    "runtime~main": [
      179,
      532,
      1303
    ],
    "01a85c17": [
      532,
      4013
    ],
    "03d40892": [
      1068
    ],
    "0e384e19": [
      9671
    ],
    "14eb3368": [
      532,
      9817
    ],
    "18c41134": [
      2859
    ],
    "1be78505": [
      532,
      4972
    ],
    "1e4232ab": [
      8818
    ],
    "1f391b9e": [
      532,
      7654,
      3085
    ],
    "21554ef4": [
      8927
    ],
    "33189a47": [
      2767
    ],
    "393be207": [
      7414
    ],
    "41ba8f77": [
      5297
    ],
    "4933cd10": [
      9194
    ],
    "533a09ca": [
      4607
    ],
    "5bfaa754": [
      217
    ],
    "5c868d36": [
      5589
    ],
    "632e2202": [
      7596
    ],
    "6875c492": [
      532,
      2529,
      7654,
      8610
    ],
    "73664a40": [
      3514
    ],
    "7661071f": [
      9642
    ],
    "814f3328": [
      2535
    ],
    "822bd8ab": [
      6504
    ],
    "8717b14a": [
      948
    ],
    "874605ca": [
      23
    ],
    "925b3f96": [
      9003
    ],
    "935f2afb": [
      53
    ],
    "9e4087bc": [
      3608
    ],
    "a2f0e6fe": [
      4906
    ],
    "a6aa9e1f": [
      532,
      2529,
      7654,
      3089
    ],
    "bfe00e9e": [
      1794
    ],
    "c4f5d8e4": [
      532,
      2004,
      4195
    ],
    "c545cbaa": [
      2848
    ],
    "c7fbe5b9": [
      4153
    ],
    "ccc49370": [
      532,
      2529,
      7654,
      6103
    ],
    "d4a2f37d": [
      6150
    ],
    "d802d782": [
      3255
    ],
    "d96357e4": [
      343
    ],
    "d9af1ab7": [
      6834
    ],
    "d9f32620": [
      1914
    ],
    "dff1c289": [
      3792
    ],
    "e273c56f": [
      2362
    ],
    "e44a2883": [
      6755
    ],
    "f3967615": [
      7476
    ],
    "f4f34a3a": [
      8636
    ],
    "f55d3e7a": [
      4193
    ],
    "styles": [
      179,
      1303,
      2004,
      2529,
      3085,
      3089,
      4013,
      4195,
      6103,
      7654,
      7918,
      8610,
      9514,
      9817,
      532
    ]
  },
  "assets": {
    "23": {
      "js": [
        {
          "file": "assets/js/874605ca.ba54b4a2.js",
          "hash": "3270dbdfbeccd1db",
          "publicPath": "/PwshBlog/assets/js/874605ca.ba54b4a2.js"
        }
      ]
    },
    "53": {
      "js": [
        {
          "file": "assets/js/935f2afb.2bd11ab6.js",
          "hash": "74b68de252ee314b",
          "publicPath": "/PwshBlog/assets/js/935f2afb.2bd11ab6.js"
        }
      ]
    },
    "179": {
      "js": [
        {
          "file": "assets/js/main.10e0167b.js",
          "hash": "eae9e510f7c44e80",
          "publicPath": "/PwshBlog/assets/js/main.10e0167b.js"
        }
      ]
    },
    "217": {
      "js": [
        {
          "file": "assets/js/5bfaa754.8752153a.js",
          "hash": "76e8d90e2964a2d6",
          "publicPath": "/PwshBlog/assets/js/5bfaa754.8752153a.js"
        }
      ]
    },
    "343": {
      "js": [
        {
          "file": "assets/js/d96357e4.b774a7a1.js",
          "hash": "58524898dd2e6372",
          "publicPath": "/PwshBlog/assets/js/d96357e4.b774a7a1.js"
        }
      ]
    },
    "532": {
      "css": [
        {
          "file": "assets/css/styles.37ec75c4.css",
          "hash": "a734a8760927d5dd",
          "publicPath": "/PwshBlog/assets/css/styles.37ec75c4.css"
        }
      ]
    },
    "948": {
      "js": [
        {
          "file": "assets/js/8717b14a.34025769.js",
          "hash": "7accd7bc9ea4fdeb",
          "publicPath": "/PwshBlog/assets/js/8717b14a.34025769.js"
        }
      ]
    },
    "1068": {
      "js": [
        {
          "file": "assets/js/03d40892.edd3682f.js",
          "hash": "633f6df67809bbf5",
          "publicPath": "/PwshBlog/assets/js/03d40892.edd3682f.js"
        }
      ]
    },
    "1303": {
      "js": [
        {
          "file": "assets/js/runtime~main.57d33be1.js",
          "hash": "9661c23f3d65b42b",
          "publicPath": "/PwshBlog/assets/js/runtime~main.57d33be1.js"
        }
      ]
    },
    "1794": {
      "js": [
        {
          "file": "assets/js/bfe00e9e.0a386ab6.js",
          "hash": "06f901304be62aea",
          "publicPath": "/PwshBlog/assets/js/bfe00e9e.0a386ab6.js"
        }
      ]
    },
    "1914": {
      "js": [
        {
          "file": "assets/js/d9f32620.171ab306.js",
          "hash": "28ee28f20f3f4fee",
          "publicPath": "/PwshBlog/assets/js/d9f32620.171ab306.js"
        }
      ]
    },
    "2004": {
      "js": [
        {
          "file": "assets/js/2004.8cedf098.js",
          "hash": "5850ddd75bddfe54",
          "publicPath": "/PwshBlog/assets/js/2004.8cedf098.js"
        }
      ]
    },
    "2267": {
      "js": [
        {
          "file": "assets/js/59362658.c444b69f.js",
          "hash": "5e9062c7d7b9eb7e",
          "publicPath": "/PwshBlog/assets/js/59362658.c444b69f.js"
        }
      ]
    },
    "2362": {
      "js": [
        {
          "file": "assets/js/e273c56f.5e36c7c1.js",
          "hash": "0dc59d560042e4c2",
          "publicPath": "/PwshBlog/assets/js/e273c56f.5e36c7c1.js"
        }
      ]
    },
    "2529": {
      "js": [
        {
          "file": "assets/js/2529.f8291257.js",
          "hash": "43c82672f770ed66",
          "publicPath": "/PwshBlog/assets/js/2529.f8291257.js"
        }
      ]
    },
    "2535": {
      "js": [
        {
          "file": "assets/js/814f3328.b65d9237.js",
          "hash": "624ce58a242e3dab",
          "publicPath": "/PwshBlog/assets/js/814f3328.b65d9237.js"
        }
      ]
    },
    "2767": {
      "js": [
        {
          "file": "assets/js/33189a47.be2f600e.js",
          "hash": "d6ee1e6a3ec9ff6f",
          "publicPath": "/PwshBlog/assets/js/33189a47.be2f600e.js"
        }
      ]
    },
    "2848": {
      "js": [
        {
          "file": "assets/js/c545cbaa.c8d0a79b.js",
          "hash": "24d460677f032108",
          "publicPath": "/PwshBlog/assets/js/c545cbaa.c8d0a79b.js"
        }
      ]
    },
    "2859": {
      "js": [
        {
          "file": "assets/js/18c41134.fb60146b.js",
          "hash": "39af027aa3dceec7",
          "publicPath": "/PwshBlog/assets/js/18c41134.fb60146b.js"
        }
      ]
    },
    "3085": {
      "js": [
        {
          "file": "assets/js/1f391b9e.25194998.js",
          "hash": "f60a6d125661b114",
          "publicPath": "/PwshBlog/assets/js/1f391b9e.25194998.js"
        }
      ]
    },
    "3089": {
      "js": [
        {
          "file": "assets/js/a6aa9e1f.6183b016.js",
          "hash": "3095500976f90727",
          "publicPath": "/PwshBlog/assets/js/a6aa9e1f.6183b016.js"
        }
      ]
    },
    "3255": {
      "js": [
        {
          "file": "assets/js/d802d782.11888ad3.js",
          "hash": "709ce9eebb98af08",
          "publicPath": "/PwshBlog/assets/js/d802d782.11888ad3.js"
        }
      ]
    },
    "3514": {
      "js": [
        {
          "file": "assets/js/73664a40.25fa13b3.js",
          "hash": "246505fc0232e566",
          "publicPath": "/PwshBlog/assets/js/73664a40.25fa13b3.js"
        }
      ]
    },
    "3608": {
      "js": [
        {
          "file": "assets/js/9e4087bc.f3c0e5e2.js",
          "hash": "18a2ad54aba6e41b",
          "publicPath": "/PwshBlog/assets/js/9e4087bc.f3c0e5e2.js"
        }
      ]
    },
    "3792": {
      "js": [
        {
          "file": "assets/js/dff1c289.68791521.js",
          "hash": "b1162377d6299f8c",
          "publicPath": "/PwshBlog/assets/js/dff1c289.68791521.js"
        }
      ]
    },
    "4013": {
      "js": [
        {
          "file": "assets/js/01a85c17.256dfc1b.js",
          "hash": "a5f81744b7ce6f84",
          "publicPath": "/PwshBlog/assets/js/01a85c17.256dfc1b.js"
        }
      ]
    },
    "4153": {
      "js": [
        {
          "file": "assets/js/c7fbe5b9.ebd29ec8.js",
          "hash": "96acc0901b9b7707",
          "publicPath": "/PwshBlog/assets/js/c7fbe5b9.ebd29ec8.js"
        }
      ]
    },
    "4193": {
      "js": [
        {
          "file": "assets/js/f55d3e7a.ecdb144d.js",
          "hash": "d9a5bdb654c26f01",
          "publicPath": "/PwshBlog/assets/js/f55d3e7a.ecdb144d.js"
        }
      ]
    },
    "4195": {
      "js": [
        {
          "file": "assets/js/c4f5d8e4.0bd52e7a.js",
          "hash": "55c61e81dcf98ce9",
          "publicPath": "/PwshBlog/assets/js/c4f5d8e4.0bd52e7a.js"
        }
      ]
    },
    "4607": {
      "js": [
        {
          "file": "assets/js/533a09ca.462358d4.js",
          "hash": "e7e5406db624f124",
          "publicPath": "/PwshBlog/assets/js/533a09ca.462358d4.js"
        }
      ]
    },
    "4906": {
      "js": [
        {
          "file": "assets/js/a2f0e6fe.284df6c1.js",
          "hash": "fbf537bd28d32072",
          "publicPath": "/PwshBlog/assets/js/a2f0e6fe.284df6c1.js"
        }
      ]
    },
    "4972": {
      "js": [
        {
          "file": "assets/js/4972.21fd2382.js",
          "hash": "afd1732615a5d57e",
          "publicPath": "/PwshBlog/assets/js/4972.21fd2382.js"
        },
        {
          "file": "assets/js/1be78505.0eeb8921.js",
          "hash": "1726bb4583af9c7c",
          "publicPath": "/PwshBlog/assets/js/1be78505.0eeb8921.js"
        }
      ]
    },
    "5297": {
      "js": [
        {
          "file": "assets/js/41ba8f77.95b6bd45.js",
          "hash": "b8d9cb7e3dbc31a1",
          "publicPath": "/PwshBlog/assets/js/41ba8f77.95b6bd45.js"
        }
      ]
    },
    "5589": {
      "js": [
        {
          "file": "assets/js/5c868d36.eecd34c8.js",
          "hash": "a2c8ec7232d9834e",
          "publicPath": "/PwshBlog/assets/js/5c868d36.eecd34c8.js"
        }
      ]
    },
    "6103": {
      "js": [
        {
          "file": "assets/js/ccc49370.363c3290.js",
          "hash": "43e885f5a80be90f",
          "publicPath": "/PwshBlog/assets/js/ccc49370.363c3290.js"
        }
      ]
    },
    "6150": {
      "js": [
        {
          "file": "assets/js/d4a2f37d.e189dd70.js",
          "hash": "45bb0ec658cbdfe4",
          "publicPath": "/PwshBlog/assets/js/d4a2f37d.e189dd70.js"
        }
      ]
    },
    "6504": {
      "js": [
        {
          "file": "assets/js/822bd8ab.ab1e7fbf.js",
          "hash": "501359ac055a6ecc",
          "publicPath": "/PwshBlog/assets/js/822bd8ab.ab1e7fbf.js"
        }
      ]
    },
    "6755": {
      "js": [
        {
          "file": "assets/js/e44a2883.0eb3a765.js",
          "hash": "2b8a476cc50612d5",
          "publicPath": "/PwshBlog/assets/js/e44a2883.0eb3a765.js"
        }
      ]
    },
    "6834": {
      "js": [
        {
          "file": "assets/js/d9af1ab7.64e28555.js",
          "hash": "6dc9414db54ef9f0",
          "publicPath": "/PwshBlog/assets/js/d9af1ab7.64e28555.js"
        }
      ]
    },
    "7414": {
      "js": [
        {
          "file": "assets/js/393be207.593ac5e6.js",
          "hash": "a7835f2f41c4cbfa",
          "publicPath": "/PwshBlog/assets/js/393be207.593ac5e6.js"
        }
      ]
    },
    "7476": {
      "js": [
        {
          "file": "assets/js/f3967615.256c20aa.js",
          "hash": "373f061fdd49d9c1",
          "publicPath": "/PwshBlog/assets/js/f3967615.256c20aa.js"
        }
      ]
    },
    "7596": {
      "js": [
        {
          "file": "assets/js/632e2202.02ca709b.js",
          "hash": "138bba39bf5e418a",
          "publicPath": "/PwshBlog/assets/js/632e2202.02ca709b.js"
        }
      ]
    },
    "7654": {
      "js": [
        {
          "file": "assets/js/7654.65c00baf.js",
          "hash": "1fbdeb6cb0efc1d2",
          "publicPath": "/PwshBlog/assets/js/7654.65c00baf.js"
        }
      ]
    },
    "7918": {
      "js": [
        {
          "file": "assets/js/17896441.0a400339.js",
          "hash": "39dce6e540281b73",
          "publicPath": "/PwshBlog/assets/js/17896441.0a400339.js"
        }
      ]
    },
    "8610": {
      "js": [
        {
          "file": "assets/js/6875c492.666cfda8.js",
          "hash": "edcef08936786d28",
          "publicPath": "/PwshBlog/assets/js/6875c492.666cfda8.js"
        }
      ]
    },
    "8636": {
      "js": [
        {
          "file": "assets/js/f4f34a3a.f045d34c.js",
          "hash": "beba6ead96edc5b4",
          "publicPath": "/PwshBlog/assets/js/f4f34a3a.f045d34c.js"
        }
      ]
    },
    "8818": {
      "js": [
        {
          "file": "assets/js/1e4232ab.db35c5a3.js",
          "hash": "dbbe37125d512102",
          "publicPath": "/PwshBlog/assets/js/1e4232ab.db35c5a3.js"
        }
      ]
    },
    "8927": {
      "js": [
        {
          "file": "assets/js/21554ef4.f81b42e0.js",
          "hash": "812c849a8f8b0a27",
          "publicPath": "/PwshBlog/assets/js/21554ef4.f81b42e0.js"
        }
      ]
    },
    "9003": {
      "js": [
        {
          "file": "assets/js/925b3f96.e96776fb.js",
          "hash": "9330e7d13e9f968e",
          "publicPath": "/PwshBlog/assets/js/925b3f96.e96776fb.js"
        }
      ]
    },
    "9194": {
      "js": [
        {
          "file": "assets/js/4933cd10.4693624d.js",
          "hash": "f8b4e10fed6808bf",
          "publicPath": "/PwshBlog/assets/js/4933cd10.4693624d.js"
        }
      ]
    },
    "9642": {
      "js": [
        {
          "file": "assets/js/7661071f.c8868612.js",
          "hash": "33288c966cdb0781",
          "publicPath": "/PwshBlog/assets/js/7661071f.c8868612.js"
        }
      ]
    },
    "9671": {
      "js": [
        {
          "file": "assets/js/0e384e19.88136090.js",
          "hash": "731c06830d2ec456",
          "publicPath": "/PwshBlog/assets/js/0e384e19.88136090.js"
        }
      ]
    },
    "9817": {
      "js": [
        {
          "file": "assets/js/14eb3368.ed139ae6.js",
          "hash": "1c0c8e02cb11fc8a",
          "publicPath": "/PwshBlog/assets/js/14eb3368.ed139ae6.js"
        }
      ]
    }
  }
}